fontdownloader/__init__.py
fontdownloader/cli.py
fontdownloader/download_catalog.py
fontdownloader-0.1.5.dist-info/licenses/LICENSE
tests/__init__.py
tests/test_cli.py
fontdownloader-0.1.5.dist-info/METADATA
fontdownloader-0.1.5.dist-info/WHEEL
fontdownloader-0.1.5.dist-info/entry_points.txt
fontdownloader-0.1.5.dist-info/top_level.txt
fontdownloader-0.1.5.dist-info/RECORD
