Metadata-Version: 2.4
Name: fontdownloader
Version: 0.1.5
Summary: CLI to download Google Fonts (TTF/OTF/TTC + WOFF), OFL license, and SCSS
Author: Mauc
License: MIT
Requires-Python: >=3.8
License-File: LICENSE
Requires-Dist: click
Requires-Dist: requests
Requires-Dist: beautifulsoup4
Provides-Extra: dev
Requires-Dist: ruff; extra == "dev"
Requires-Dist: pytest; extra == "dev"
Dynamic: license-file
